novalad/__init__.py
novalad/api/__init__.py
novalad/api/base.py
novalad/api/client.py
novalad/api/config.py
novalad/api/exception.py
novalad/render/__init__.py
novalad/render/graph.py
novalad/render/layout.py
novalad/render/md.py
novalad/utils/__init__.py
novalad/utils/io.py
novalad/utils/progress.py
novalad-0.1.16.dist-info/LICENSE
novalad-0.1.16.dist-info/METADATA
novalad-0.1.16.dist-info/WHEEL
novalad-0.1.16.dist-info/RECORD
