Metadata-Version: 2.3
Name: novalad
Version: 0.1.16
Summary: Novalad: AI-powered platform for transforming unstructured documents like PDFs and PowerPoints into machine-readable, structured data.
License: Apache-2.0
Keywords: AI,PDF,PowerPoint,data extraction,document parsing,unstructured data,layout parser
Author: Novalad
Author-email: info@novalad.ai
Requires-Python: >=3.8
Classifier: License :: OSI Approved :: Apache Software License
Classifier: Programming Language :: Python :: 3
Classifier: Programming Language :: Python :: 3.8
Classifier: Programming Language :: Python :: 3.9
Classifier: Programming Language :: Python :: 3.10
Classifier: Programming Language :: Python :: 3.11
Classifier: Programming Language :: Python :: 3.12
Classifier: Programming Language :: Python :: 3.13
Requires-Dist: PyMuPDF
Requires-Dist: dash
Requires-Dist: dash_cytoscape
Requires-Dist: httpx
Requires-Dist: jupyter-dash
Requires-Dist: markdown
Requires-Dist: matplotlib
Requires-Dist: numpy
Requires-Dist: opencv-python
Requires-Dist: pandas
Requires-Dist: pillow
Requires-Dist: requests
Requires-Dist: tqdm
Project-URL: API Docs, https://novalad.apidog.io/
Project-URL: Documentation, https://www.novalad.ai
Project-URL: Google Colab, https://colab.research.google.com/gist/connectaman/92cbb44bcb17a474e32ce9c194effb97/novalad-demo.ipynb
Project-URL: Homepage, https://www.novalad.ai
Project-URL: Repository, https://github.com/novaladai
